LICENSE.md
MANIFEST.in
setup.cfg
setup.py
murpy/__init__.py
murpy.egg-info/PKG-INFO
murpy.egg-info/SOURCES.txt
murpy.egg-info/dependency_links.txt
murpy.egg-info/top_level.txt
murpy/commands/__init__.py
murpy/commands/controlflow/IF.py
murpy/commands/controlflow/__init__.py
murpy/commands/memory/__init__.py
murpy/commands/memory/stack.py
murpy/commands/operators/__init__.py
murpy/commands/operators/compare.py
murpy/commands/operators/math.py
murpy/compiletools/__init__.py
murpy/core/__init__.py
murpy/core/objects/__init__.py
murpy/core/objects/memory.py
murpy/core/operations/__init__.py
murpy/core/operations/compare.py
murpy/core/operations/controlflow.py
murpy/core/operations/math.py
murpy/core/operations/memory.py
murpy/core/operations/special.py